{
  "[087]CAN( battery_temp_44)": "0",
  "[128]CAN( battery_temp_5)": "25",
  "[114]CAN( battery_temp_23)": "0",
  "[121]CAN( battery_temp_14)": "0",
  "水冷机采样温度": "0",
  "水冷机出液口流量PV": "0",
  "[002]CAN( SlowChargePosTemp)": "-40",
  "[211]CAN( battery_ODT)": "0",
  "[056]CAN( battery_volt_73)": "2.854",
  "[003]CAN( SlowChargeNogTemp)": "-40",
  "[169]CAN( battery_volt_10)": "2.508",
  "[134]CAN( battery_volt_47)": "2.821",
  "End Time": "",
  "[049]CAN( battery_volt_82)": "2.917",
  "[076]CAN( battery_volt_53)": "2.851",
  "水冷机进液口温度PV": "0",
  "[189]CAN( battery_low_temperature)": "25",
  "[052]CAN( battery_volt_77)": "2.925",
  "[042]CAN( battery_volt_91)": "2.859",
  "[108]CAN( battery_temp_17)": "0",
  "[138]CAN( battery_volt_43)": "2.85",
  "Code": "",
  "[165]CAN( battery_volt_14)": "2.822",
  "[148]CAN( battery_volt_29)": "2.867",
  "[090]CAN( battery_temp_47)": "0",
  "[107]CAN( battery_temp_32)": "0",
  "[141]CAN( battery_volt_38)": "2.852",
  "作业时间": "14:00:08",
  "[210]CAN( battery_OLT)": "0",
  "作日日期": "2022/8/16",
  "[127]CAN( battery_temp_4)": "25",
  "[132]CAN( battery_volt_45)": "2.911",
  "Avg. Vtg": "293.62",
  "充电能量(Wh)": "0",
  "[156]CAN( battery_volt_21)": "2.871",
  "[185]CAN( NegRelaySts)": "1",
  "[209]CAN( battery_OCC)": "0",
  "[101]CAN( battery_temp_26)": "0",
  "[001]CAN( FastChargePOS)": "-40",
  "[034]CAN( battery_volt_99)": "2.855",
  "Voltage Bus": "",
  "[197]CAN( total_current)": "0.000048",
  "[183]CAN( charge_relay_state)": "0",
  "[149]CAN( battery_volt_30)": "2.862",
  "[188]CAN( battery_high_temperature_NO)": "1",
  "水冷机温度SP": "0",
  "[080]CAN( battery_volt_49)": "2.868",
  "[021]CAN( battery_volt_110)": "0",
  "AccCycle2": "0",
  "AccCycle1": "0",
  "AccCycle4": "0",
  "[023]CAN( battery_volt_112)": "0",
  "AccCycle3": "0",
  "[196]CAN( total_voltage)": "295.800018",
  "[069]CAN( battery_volt_62)": "2.908",
  "[158]CAN( battery_volt_23)": "2.867",
  "OutputState": "",
  "[032]CAN( battery_volt_97)": "2.874",
  "[111]CAN( battery_temp_20)": "0",
  "[004]CAN( Liquid_In_Temperature)": "-40",
  "AccCycle5": "0",
  "[015]CAN( battery_volt_120)": "0",
  "[167]CAN( battery_volt_16)": "2.912",
  "[051]CAN( battery_volt_84)": "2.888",
  "[078]CAN( battery_volt_55)": "2.84",
  "[171]CAN( battery_volt_12)": "2.677",
  "[047]CAN( battery_volt_88)": "2.814",
  "[070]CAN( battery_volt_63)": "2.937",
  "[059]CAN( battery_volt_76)": "2.863",
  "[082]CAN( battery_volt_51)": "2.853",
  "水冷机压力SP": "0",
  "[176]CAN( battery_volt_1)": "2.806",
  "[162]CAN( battery_volt_19)": "2.841",
  "[193]CAN( battery_high_voltage_NO)": "90",
  "[073]CAN( battery_volt_58)": "2.852",
  "[105]CAN( battery_temp_30)": "0",
  "[030]CAN( battery_volt_103)": "2.923",
  "CV Time": "0",
  "Work Time": "",
  "Capacitance(F)": "0",
  "[035]CAN( battery_volt_100)": "2.916",
  "[099]CAN( battery_temp_40)": "0",
  "[084]CAN( battery_temp_41)": "0",
  "[168]CAN( battery_volt_9)": "2.703",
  "水冷机进液口压力PV": "0",
  "[010]CAN( HV2)": "297.600006",
  "[130]CAN( battery_temp_7)": "25",
  "[007]CAN( DisCharge_Port_NogTemp)": "25",
  "[089]CAN( battery_temp_46)": "0",
  "[123]CAN( battery_temp_16)": "0",
  "[212]CAN( battery_ODV)": "0",
  "水冷机流量SP": "0",
  "[172]CAN( battery_volt_5)": "2.627",
  "[194]CAN( battery_low_voltage)": "2.484",
  "水冷机出液口温度PV": "0",
  "MULTICycle4": "",
  "MULTICycle3": "",
  "Voltage Input": "",
  "State": "",
  "[067]CAN( battery_volt_68)": "2.872",
  "MULTICycle2": "",
  "MULTICycle1": "",
  "[058]CAN( battery_volt_75)": "2.845",
  "[060]CAN( battery_volt_69)": "2.813",
  "MULTICycle5": "",
  "TotCycle": "1",
  "[009]CAN( HV1)": "0",
  "[083]CAN( battery_volt_52)": "2.87",
  "[017]CAN( battery_volt_114)": "0",
  "Energy(Wh)": "0",
  "[019]CAN( battery_volt_116)": "0",
  "[147]CAN( battery_volt_36)": "2.827",
  "[203]CAN( battery_LSOC)": "0",
  "[062]CAN( battery_volt_71)": "2.924",
  "[012]CAN( battery_volt_117)": "0",
  "[014]CAN( battery_volt_119)": "0",
  "[028]CAN( battery_volt_101)": "2.856",
  "Power(W)": "-26.027",
  "[025]CAN( battery_volt_106)": "0",
  "[050]CAN( battery_volt_83)": "2.921",
  "[151]CAN( battery_volt_32)": "2.921",
  "放电能量(Wh)": "-0.447",
  "TotTime": "D0 00:01:59.00",
  "Impedance(MOhm)": "0",
  "[027]CAN( battery_volt_108)": "0",
  "[020]CAN( battery_volt_109)": "0",
  "[072]CAN( battery_volt_57)": "2.838",
  "[161]CAN( battery_volt_18)": "2.765",
  "Voltage Power": "",
  "[085]CAN( battery_temp_42)": "0",
  "[008]CAN( PACK)": "297.600006",
  "[038]CAN( battery_volt_95)": "2.858",
  "[079]CAN( battery_volt_56)": "2.866",
  "[125]CAN( battery_temp_2)": "25",
  "[040]CAN( battery_volt_89)": "2.821",
  "水冷机出液口压力PV": "0",
  "[104]CAN( battery_temp_29)": "0",
  "Schedule": "BZFD-1CCD",
  "[118]CAN( battery_temp_11)": "0",
  "[152]CAN( battery_volt_25)": "2.804",
  "[071]CAN( battery_volt_64)": "2.871",
  "DataSequence": "124",
  "[159]CAN( battery_volt_24)": "2.842",
  "[094]CAN( battery_temp_35)": "0",
  "[174]CAN( battery_volt_7)": "2.57",
  "Meter": "0",
  "[091]CAN( battery_temp_48)": "0",
  "总容量(Ah)": "-0.362",
  "[140]CAN( battery_volt_37)": "2.85",
  "[195]CAN( battery_low_voltage_NO)": "8",
  "[199]CAN( battery_OHV)": "0",
  "[044]CAN( battery_volt_85)": "2.93",
  "[214]CAN( battery_short)": "0",
  "Capacity": "",
  "[117]CAN( battery_temp_10)": "0",
  "[178]CAN( battery_volt_3)": "2.708",
  "[068]CAN( battery_volt_61)": "2.89",
  "[146]CAN( battery_volt_35)": "2.879",
  "[207]CAN( battery_OHTV)": "0",
  "[157]CAN( battery_volt_22)": "2.842",
  "[041]CAN( battery_volt_90)": "2.94",
  "[061]CAN( battery_volt_70)": "2.84",
  "[187]CAN( battery_high_temperature)": "25",
  "[205]CAN( battery_ULeak)": "0",
  "TestName": "DJ2136(L)-BZFD-1CCD-2022.8.16-13.57-WYP",
  "[150]CAN( battery_volt_31)": "2.844",
  "StepTime": "D0 00:01:01.00",
  "[180]CAN( Negative_insu_res)": "3364.900146",
  "[057]CAN( battery_volt_74)": "2.887",
  "温箱湿度(%)": "0",
  "[133]CAN( battery_volt_46)": "2.825",
  "放电容量(Ah)": "0",
  "[098]CAN( battery_temp_39)": "0",
  "[115]CAN( battery_temp_24)": "0",
  "[005]CAN( Liquid_Out_Temperature)": "-40",
  "[124]CAN( battery_temp_1)": "25",
  "Module": "M01Ch01[001]",
  "[100]CAN( battery_temp_25)": "0",
  "[164]CAN( battery_volt_13)": "2.813",
  "[139]CAN( battery_volt_44)": "2.921",
  "CurCycle": "1",
  "[208]CAN( battery_OLTV)": "0",
  "[095]CAN( battery_temp_36)": "0",
  "[043]CAN( battery_volt_92)": "2.915",
  "[106]CAN( battery_temp_31)": "0",
  "[109]CAN( battery_temp_18)": "0",
  "[163]CAN( battery_volt_20)": "2.904",
  "[160]CAN( battery_volt_17)": "2.829",
  "[039]CAN( battery_volt_96)": "2.901",
  "[135]CAN( battery_volt_48)": "2.893",
  "[048]CAN( battery_volt_81)": "2.855",
  "[116]CAN( battery_temp_9)": "0",
  "[137]CAN( battery_volt_42)": "2.847",
  "[131]CAN( battery_temp_8)": "25",
  "[182]CAN( discharge_relay_state)": "1",
  "[184]CAN( precharge_relay_state)": "0",
  "[088]CAN( battery_temp_45)": "0",
  "[122]CAN( battery_temp_15)": "0",
  "[170]CAN( battery_volt_11)": "2.751",
  "[053]CAN( battery_volt_78)": "2.88",
  "[110]CAN( battery_temp_19)": "0",
  "[113]CAN( battery_temp_22)": "0",
  "[081]CAN( battery_volt_50)": "2.789",
  "[037]CAN( battery_volt_94)": "2.849",
  "[179]CAN( battery_volt_4)": "2.861",
  "[190]CAN( battery_low_temperature_NO)": "1",
  "[202]CAN( battery_ODC)": "1",
  "SOC": "0",
  "[022]CAN( battery_volt_111)": "0",
  "[103]CAN( battery_temp_28)": "0",
  "[064]CAN( battery_volt_65)": "2.935",
  "[119]CAN( battery_temp_12)": "0",
  "[153]CAN( battery_volt_26)": "2.853",
  "[093]CAN( battery_temp_34)": "0",
  "CV Day": "0",
  "[143]CAN( battery_volt_40)": "2.89",
  "Type": "Rest",
  "Serial": "C",
  "[046]CAN( battery_volt_87)": "2.917",
  "[011]CAN( LINK)": "299.100006",
  "[086]CAN( battery_temp_43)": "0",
  "[120]CAN( battery_temp_13)": "0",
  "充电容量(Ah)": "0",
  "[063]CAN( battery_volt_72)": "2.855",
  "[175]CAN( battery_volt_8)": "2.483",
  "[144]CAN( battery_volt_33)": "2.899",
  "[206]CAN( battery_comm_abort)": "0",
  "[136]CAN( battery_volt_41)": "2.844",
  "[066]CAN( battery_volt_67)": "2.923",
  "[186]CAN( BatteryVol)": "12.2",
  "[204]CAN( battery_Leak)": "0",
  "总能量(Wh)": "-103.495",
  "[075]CAN( battery_volt_60)": "2.829",
  "LoadVlotage": "0",
  "[126]CAN( battery_temp_3)": "25",
  "Start Time": "",
  "[191]CAN( Positive_insu_res)": "3368.300049",
  "[054]CAN( battery_volt_79)": "2.898",
  "[155]CAN( battery_volt_28)": "2.859",
  "[031]CAN( battery_volt_104)": "2.853",
  "[096]CAN( battery_temp_37)": "0",
  "LoadCurrent": "0.000/0.000",
  "[102]CAN( battery_temp_27)": "0",
  "CommState": "8",
  "温箱温度(`C)": "0",
  "[097]CAN( battery_temp_38)": "0",
  "Channel": "M01Ch01[001]",
  "累积充电E": "0",
  "[142]CAN( battery_volt_39)": "2.807",
  "Grade": "",
  "[006]CAN( DisCharge_Port_PosTemp)": "-40",
  "[201]CAN( battery_OHT)": "0",
  "累积充电C": "0",
  "Voltage(V)": "295.803",
  "[181]CAN( SOH)": "99.800003",
  "[198]CAN( SOC)": "0",
  "[074]CAN( battery_volt_59)": "2.917",
  "[055]CAN( battery_volt_80)": "2.889",
  "[016]CAN( battery_volt_113)": "0",
  "累积放电C": "-0.362",
  "[018]CAN( battery_volt_115)": "0",
  "累积放电E": "-103.495",
  "Avg. Crt": "-0.087",
  "InputState": "",
  "[013]CAN( battery_volt_118)": "0",
  "[129]CAN( battery_temp_6)": "25",
  "[036]CAN( battery_volt_93)": "2.792",
  "[077]CAN( battery_volt_54)": "2.845",
  "[026]CAN( battery_volt_107)": "0",
  "[166]CAN( battery_volt_15)": "2.83",
  "[177]CAN( battery_volt_2)": "2.572",
  "[029]CAN( battery_volt_102)": "2.896",
  "[024]CAN( battery_volt_105)": "0",
  "[092]CAN( battery_temp_33)": "0",
  "[065]CAN( battery_volt_66)": "2.847",
  "[154]CAN( battery_volt_27)": "2.891",
  "Current(A)": "0",
  "[033]CAN( battery_volt_98)": "2.848",
  "[213]CAN( battery_temp_rise)": "0",
  "[045]CAN( battery_volt_86)": "2.914",
  "[112]CAN( battery_temp_21)": "0",
  "[145]CAN( battery_volt_34)": "2.838",
  "[192]CAN( battery_high_voltage)": "2.941",
  "[173]CAN( battery_volt_6)": "2.75",
  "StepNo": "6",
  "[200]CAN( battery_OLV)": "0"
}
{
  "End Time": "",
  "State": "",
  "Capa. Sum": "-0.362",
  "Working Date": "2022/8/16",
  "TotCycle": "1",
  "Power(W)": "-26.027",
  "TotTime": "D0 00:01:59.00",
  "Char. Cap.(Ah)": "0",
  "ChargeWh(Wh)": "0",
  "StepTime": "D0 00:01:01.00",
  "CurCycle": "1",
  "Working Time": "14:00:08",
  "DisChargeWh(Wh)": "-0.447",
  "Type": "Rest",
  "Total_energy(Wh)": "-103.495",
  "Start Time": "",
  "Dischar. Cap.(Ah)": "0",
  "Voltage(V)": "295.803",
  "Current(A)": "0",
  "StepNo": "6"
}
